pystac/__init__.py
pystac/asset.py
pystac/cache.py
pystac/catalog.py
pystac/client.py
pystac/collection.py
pystac/common_metadata.py
pystac/errors.py
pystac/item.py
pystac/item_assets.py
pystac/item_collection.py
pystac/layout.py
pystac/link.py
pystac/media_type.py
pystac/provider.py
pystac/py.typed
pystac/rel_type.py
pystac/stac_io.py
pystac/stac_object.py
pystac/summaries.py
pystac/utils.py
pystac/version.py
pystac/extensions/__init__.py
pystac/extensions/base.py
pystac/extensions/classification.py
pystac/extensions/datacube.py
pystac/extensions/eo.py
pystac/extensions/ext.py
pystac/extensions/file.py
pystac/extensions/grid.py
pystac/extensions/hooks.py
pystac/extensions/item_assets.py
pystac/extensions/label.py
pystac/extensions/mgrs.py
pystac/extensions/mlm.py
pystac/extensions/pointcloud.py
pystac/extensions/projection.py
pystac/extensions/raster.py
pystac/extensions/render.py
pystac/extensions/sar.py
pystac/extensions/sat.py
pystac/extensions/scientific.py
pystac/extensions/storage.py
pystac/extensions/table.py
pystac/extensions/timestamps.py
pystac/extensions/version.py
pystac/extensions/view.py
pystac/extensions/xarray_assets.py
pystac/html/JSON.jinja2
pystac/html/Macros.jinja2
pystac/html/__init__.py
pystac/html/jinja_env.py
pystac/serialization/__init__.py
pystac/serialization/common_properties.py
pystac/serialization/identify.py
pystac/serialization/migrate.py
pystac/static/__init__.py
pystac/static/fields-normalized.json
pystac/validation/__init__.py
pystac/validation/local_validator.py
pystac/validation/schema_uri_map.py
pystac/validation/stac_validator.py
pystac/validation/jsonschemas/__init__.py
pystac/validation/jsonschemas/geojson/Feature.json
pystac/validation/jsonschemas/geojson/Geometry.json
pystac/validation/jsonschemas/stac-spec/v1.1.0/bands.json
pystac/validation/jsonschemas/stac-spec/v1.1.0/basics.json
pystac/validation/jsonschemas/stac-spec/v1.1.0/catalog.json
pystac/validation/jsonschemas/stac-spec/v1.1.0/collection.json
pystac-1.14.2.dist-info/licenses/LICENSE
pystac-1.14.2.dist-info/METADATA
pystac-1.14.2.dist-info/WHEEL
pystac-1.14.2.dist-info/top_level.txt
pystac-1.14.2.dist-info/RECORD
