Metadata-Version: 2.4
Name: pystac
Version: 1.14.2
Summary: Python library for working with the SpatioTemporal Asset Catalog (STAC) specification
Author-email: Rob Emanuele <rdemanuele@gmail.com>, Jon Duckworth <duckontheweb@gmail.com>
Maintainer-email: Pete Gadomski <pete.gadomski@gmail.com>
License: Apache-2.0
Project-URL: Documentation, https://pystac.readthedocs.io
Project-URL: Repository, https://github.com/stac-utils/pystac
Project-URL: Issues, https://github.com/stac-utils/pystac/issues
Project-URL: Changelog, https://github.com/stac-utils/pystac/blob/main/CHANGELOG.md
Project-URL: Discussions, https://github.com/radiantearth/stac-spec/discussions/categories/stac-software
Keywords: pystac,imagery,raster,catalog,STAC
Classifier: Development Status :: 5 - Production/Stable
Classifier: Intended Audience :: Developers
Classifier: License :: OSI Approved :: Apache Software License
Classifier: Natural Language :: English
Classifier: Programming Language :: Python :: 3
Classifier: Programming Language :: Python :: 3.10
Classifier: Programming Language :: Python :: 3.11
Classifier: Programming Language :: Python :: 3.12
Classifier: Programming Language :: Python :: 3.13
Requires-Python: >=3.10
License-File: LICENSE
Requires-Dist: python-dateutil>=2.7.0
Provides-Extra: jinja2
Requires-Dist: jinja2<4.0; extra == "jinja2"
Provides-Extra: orjson
Requires-Dist: orjson>=3.5; extra == "orjson"
Provides-Extra: urllib3
Requires-Dist: urllib3>=1.26; extra == "urllib3"
Provides-Extra: validation
Requires-Dist: jsonschema~=4.18; extra == "validation"
Dynamic: license-file
